{"trial_id": "9866b93679c52d7dddda4c86a26edbab", "hyperparameters": {"space": [{"class_name": "Choice", "config": {"name": "units", "default": 32, "values": [32, 64, 128, 256], "ordered": true}}, {"class_name": "Int", "config": {"name": "num_layers", "default": null, "min_value": 1, "max_value": 2, "step": 1, "sampling": null}}, {"class_name": "Choice", "config": {"name": "units_0", "default": 32, "values": [32, 64, 128, 256], "ordered": true}}, {"class_name": "Choice", "config": {"name": "learning_rate", "default": 0.01, "values": [0.01, 0.001, 0.0001], "ordered": true}}], "values": {"units": 32, "num_layers": 1, "units_0": 256, "learning_rate": 0.01}}, "metrics": {"metrics": {"loss": {"direction": "min", "observations": [{"value": [3.4525254567464194], "step": 0}]}, "accuracy": {"direction": "max", "observations": [{"value": [0.12039999788006146], "step": 0}]}, "val_loss": {"direction": "min", "observations": [{"value": [3.486447811126709], "step": 0}]}, "val_accuracy": {"direction": "max", "observations": [{"value": [0.1324657959242662], "step": 0}]}}}, "score": 0.1324657959242662, "best_step": 0, "status": "COMPLETED"}