{"graph": {"_type": "graph-file", "path": "media/graph/graph_summary_7eecb656.graph.json", "sha256": "7eecb656a83b438659481dc11be2a76ba9b12b4f5ef541ece126cd39f90d2cca", "size": 49886}, "val_loss": 0.4748935401439667, "val_accuracy": 0.8950999975204468, "epoch": 63, "examples": {"width": 32, "height": 32, "format": "png", "count": 36, "_type": "images", "captions": ["bird", "frog", "automobile", "cat", "automobile", "dog", "bird", "truck", "cat", "truck", "frog", "frog", "automobile", "cat", "automobile", "airplane", "truck", "truck", "bird", "truck", "bird", "truck", "cat", "ship", "frog", "truck", "frog", "frog", "deer", "automobile", "deer", "deer", "ship", "frog", "ship", "cat"]}, "_runtime": 4916.817846059799, "_step": 63, "loss": 0.2883751690387726, "accuracy": 0.9508341550827026, "_timestamp": 1599881599.6289542, "best_val_loss": 0.460663378238678, "best_epoch": 60}
