{"graph": {"_type": "graph-file", "path": "media/graph/graph_summary_7eecb656.graph.json", "sha256": "7eecb656a83b438659481dc11be2a76ba9b12b4f5ef541ece126cd39f90d2cca", "size": 49886}, "val_accuracy": 0.5986999869346619, "epoch": 5, "_step": 5, "examples": {"width": 32, "height": 32, "format": "png", "count": 36, "_type": "images", "captions": ["dog", "deer", "ship", "ship", "deer", "ship", "deer", "automobile", "automobile", "automobile", "dog", "cat", "deer", "dog", "ship", "ship", "bird", "truck", "truck", "dog", "dog", "airplane", "dog", "bird", "truck", "ship", "ship", "deer", "airplane", "deer", "automobile", "deer", "frog", "cat", "dog", "truck"]}, "accuracy": 0.7252600193023682, "loss": 1.1254088878631592, "_timestamp": 1599802932.6838565, "val_loss": 1.5106862783432007, "_runtime": 3103.9965059757233, "best_val_loss": 1.3846880197525024, "best_epoch": 4}
