{"graph": {"_type": "graph-file", "path": "media/graph/graph_summary_7eecb656.graph.json", "sha256": "7eecb656a83b438659481dc11be2a76ba9b12b4f5ef541ece126cd39f90d2cca", "size": 49886}, "examples": {"width": 32, "height": 32, "format": "png", "count": 36, "_type": "images", "captions": ["bird", "automobile", "frog", "airplane", "bird", "airplane", "cat", "horse", "truck", "deer", "cat", "automobile", "ship", "ship", "airplane", "truck", "bird", "automobile", "automobile", "frog", "horse", "frog", "airplane", "ship", "frog", "frog", "ship", "truck", "cat", "ship", "cat", "airplane", "automobile", "cat", "horse", "ship"]}, "epoch": 29, "_timestamp": 1599758686.1861331, "val_accuracy": 0.6653000116348267, "_runtime": 737.0093419551849, "val_loss": 1.85293710231781, "_step": 29, "loss": 0.5790255665779114, "accuracy": 0.9509999752044678, "best_val_loss": 1.514938235282898, "best_epoch": 9}
